af_adapter/__init__.py
af_adapter/impl/bert/__init__.py
af_adapter/impl/bert/att.py
af_adapter/impl/bert/ffn.py
af_adapter-0.1.0.dist-info/METADATA
af_adapter-0.1.0.dist-info/WHEEL
af_adapter-0.1.0.dist-info/RECORD
